programmabletuple/__init__.py
programmabletuple-0.5.0.dist-info/DESCRIPTION.rst
programmabletuple-0.5.0.dist-info/METADATA
programmabletuple-0.5.0.dist-info/metadata.json
programmabletuple-0.5.0.dist-info/pbr.json
programmabletuple-0.5.0.dist-info/RECORD
programmabletuple-0.5.0.dist-info/top_level.txt
programmabletuple-0.5.0.dist-info/WHEEL
