Metadata-Version: 2.0
Name: programmabletuple
Version: 0.5.0
Summary: Python metaclass for making named tuples with programmability
Home-page: https://github.com/tschijnmo/programmabletuple
Author: Tschijnmo TSCHAU
Author-email: tschijnmotschau@gmail.com
License: MIT
Platform: UNKNOWN
Classifier: License :: OSI Approved :: MIT License
Classifier: Programming Language :: Python
Classifier: Programming Language :: Python :: 3
Classifier: Topic :: Software Development :: Libraries :: Python Modules
